pyqt_dark_gray_theme/__init__.py
pyqt_dark_gray_theme/darkGrayTheme.py
pyqt_dark_gray_theme-0.0.4.dist-info/LICENSE
pyqt_dark_gray_theme-0.0.4.dist-info/METADATA
pyqt_dark_gray_theme-0.0.4.dist-info/WHEEL
pyqt_dark_gray_theme-0.0.4.dist-info/top_level.txt
pyqt_dark_gray_theme-0.0.4.dist-info/RECORD
