Metadata-Version: 2.1
Name: pyqt-dark-gray-theme
Version: 0.0.4
Summary: PyQt dark-gray theme
Home-page: https://github.com/yjg30737/pyqt-dark-gray-theme.git
Author: Jung Gyu Yoon
Author-email: yjg30737@gmail.com
License: MIT
Platform: UNKNOWN
License-File: LICENSE
Requires-Dist: PyQt5 (>=5.8)
Requires-Dist: qtsasstheme (>=0.0.1)
